{
    "/js/app.js": "/js/app.js",
    "/js/app.8777f32a1c3529038128.hot-update.js": "/js/app.8777f32a1c3529038128.hot-update.js",
    "/js/app.01714e2b7e90166cb1ea.hot-update.js": "/js/app.01714e2b7e90166cb1ea.hot-update.js",
    "/js/app.55ef6e1756a2f21aa490.hot-update.js": "/js/app.55ef6e1756a2f21aa490.hot-update.js",
    "/js/app.7d7bbe30c632855bca0c.hot-update.js": "/js/app.7d7bbe30c632855bca0c.hot-update.js",
    "/js/app.67a8cd1756593c9b4418.hot-update.js": "/js/app.67a8cd1756593c9b4418.hot-update.js",
    "/js/app.0b61d6267f64f47aa12a.hot-update.js": "/js/app.0b61d6267f64f47aa12a.hot-update.js",
    "/js/app.36a8232bdd1ef87f9991.hot-update.js": "/js/app.36a8232bdd1ef87f9991.hot-update.js",
    "/js/app.eacbf59a4c9ca6d1247e.hot-update.js": "/js/app.eacbf59a4c9ca6d1247e.hot-update.js",
    "/js/app.66ab3119515b182e9b18.hot-update.js": "/js/app.66ab3119515b182e9b18.hot-update.js",
    "/js/app.b225faeedbfc118f1c6a.hot-update.js": "/js/app.b225faeedbfc118f1c6a.hot-update.js",
    "/js/app.ed7694bfcf04a4d30c73.hot-update.js": "/js/app.ed7694bfcf04a4d30c73.hot-update.js",
    "/js/app.a86465e6cf27f19f8dcc.hot-update.js": "/js/app.a86465e6cf27f19f8dcc.hot-update.js",
    "/js/app.296140dbd9050d35b6ae.hot-update.js": "/js/app.296140dbd9050d35b6ae.hot-update.js",
    "/js/app.8d00dbdb0d59091651c3.hot-update.js": "/js/app.8d00dbdb0d59091651c3.hot-update.js",
    "/js/app.134f08c1ccd1e97d647b.hot-update.js": "/js/app.134f08c1ccd1e97d647b.hot-update.js",
    "/js/app.f5ab1f17eaccd723ef48.hot-update.js": "/js/app.f5ab1f17eaccd723ef48.hot-update.js",
    "/js/app.638d98659351ddf23147.hot-update.js": "/js/app.638d98659351ddf23147.hot-update.js",
    "/js/app.e06ee1ae0a386a62dba6.hot-update.js": "/js/app.e06ee1ae0a386a62dba6.hot-update.js",
    "/js/app.21306d2a847f738174a1.hot-update.js": "/js/app.21306d2a847f738174a1.hot-update.js",
    "/js/app.f67cfa80367db4c60fc9.hot-update.js": "/js/app.f67cfa80367db4c60fc9.hot-update.js",
    "/js/app.752db6f35e59f1fbead0.hot-update.js": "/js/app.752db6f35e59f1fbead0.hot-update.js",
    "/js/app.58d76c3a37fca7f7d722.hot-update.js": "/js/app.58d76c3a37fca7f7d722.hot-update.js",
    "/js/app.25c821c1978a45b70e34.hot-update.js": "/js/app.25c821c1978a45b70e34.hot-update.js",
    "/js/app.726adab0f9aa25cd737b.hot-update.js": "/js/app.726adab0f9aa25cd737b.hot-update.js",
    "/js/app.7ce8f69c2de32c5abc48.hot-update.js": "/js/app.7ce8f69c2de32c5abc48.hot-update.js",
    "/js/app.437c2b47a5d9a901629a.hot-update.js": "/js/app.437c2b47a5d9a901629a.hot-update.js",
    "/js/app.b1947b81feb9597553d6.hot-update.js": "/js/app.b1947b81feb9597553d6.hot-update.js",
    "/js/app.5015d1dff9348396e69b.hot-update.js": "/js/app.5015d1dff9348396e69b.hot-update.js",
    "/js/app.ced84a07732f40ba8448.hot-update.js": "/js/app.ced84a07732f40ba8448.hot-update.js",
    "/js/app.a1f5db626199cd454089.hot-update.js": "/js/app.a1f5db626199cd454089.hot-update.js",
    "/js/app.a8e0437aec24f9a824b4.hot-update.js": "/js/app.a8e0437aec24f9a824b4.hot-update.js",
    "/js/app.8ac91b8687762d75e562.hot-update.js": "/js/app.8ac91b8687762d75e562.hot-update.js",
    "/js/app.5a781844bf4818b041d5.hot-update.js": "/js/app.5a781844bf4818b041d5.hot-update.js",
    "/js/app.ef936082c1c4d362abb1.hot-update.js": "/js/app.ef936082c1c4d362abb1.hot-update.js",
    "/js/app.2f32c79364d0a0c0ffe2.hot-update.js": "/js/app.2f32c79364d0a0c0ffe2.hot-update.js",
    "/js/app.9bdb6fef101e075cfbf2.hot-update.js": "/js/app.9bdb6fef101e075cfbf2.hot-update.js",
    "/js/app.c42407ba2b942746eecb.hot-update.js": "/js/app.c42407ba2b942746eecb.hot-update.js",
    "/js/app.3c588f9a0f1c74ef8169.hot-update.js": "/js/app.3c588f9a0f1c74ef8169.hot-update.js",
    "/js/app.817eb69f9e83c7e022df.hot-update.js": "/js/app.817eb69f9e83c7e022df.hot-update.js",
    "/js/app.81a529690f8d8a739e93.hot-update.js": "/js/app.81a529690f8d8a739e93.hot-update.js",
    "/js/app.528b69716f1b899b9b7d.hot-update.js": "/js/app.528b69716f1b899b9b7d.hot-update.js",
    "/js/app.13c5bdda84355338063c.hot-update.js": "/js/app.13c5bdda84355338063c.hot-update.js",
    "/js/app.010555e346c9e84462da.hot-update.js": "/js/app.010555e346c9e84462da.hot-update.js",
    "/js/app.6d7f4fd6f4bd2644ae85.hot-update.js": "/js/app.6d7f4fd6f4bd2644ae85.hot-update.js",
    "/js/app.9c46171874da2eb1eb04.hot-update.js": "/js/app.9c46171874da2eb1eb04.hot-update.js",
    "/js/app.38616bad102095fadfbd.hot-update.js": "/js/app.38616bad102095fadfbd.hot-update.js",
    "/js/app.8872ab9fd60845bd7cd6.hot-update.js": "/js/app.8872ab9fd60845bd7cd6.hot-update.js",
    "/js/app.be62f52d5eb9186666ee.hot-update.js": "/js/app.be62f52d5eb9186666ee.hot-update.js",
    "/js/app.bae97e680af71244c190.hot-update.js": "/js/app.bae97e680af71244c190.hot-update.js",
    "/js/app.a12e8af6b471e760bfaf.hot-update.js": "/js/app.a12e8af6b471e760bfaf.hot-update.js",
    "/js/app.65bf872ed25b2de48f25.hot-update.js": "/js/app.65bf872ed25b2de48f25.hot-update.js",
    "/js/app.2451905b41a6a6f46c8e.hot-update.js": "/js/app.2451905b41a6a6f46c8e.hot-update.js",
    "/js/app.699b42977f1b9db54d6b.hot-update.js": "/js/app.699b42977f1b9db54d6b.hot-update.js",
    "/js/app.49da6638864883aa8c61.hot-update.js": "/js/app.49da6638864883aa8c61.hot-update.js",
    "/js/app.9e7e2a3f2288711b900b.hot-update.js": "/js/app.9e7e2a3f2288711b900b.hot-update.js",
    "/js/app.0c8ede5375ea8209a8ba.hot-update.js": "/js/app.0c8ede5375ea8209a8ba.hot-update.js",
    "/js/app.df41c50ad916a23cc074.hot-update.js": "/js/app.df41c50ad916a23cc074.hot-update.js",
    "/js/app.3849255bb2c7f3948cfb.hot-update.js": "/js/app.3849255bb2c7f3948cfb.hot-update.js",
    "/js/app.cc6fcaff7815e4413348.hot-update.js": "/js/app.cc6fcaff7815e4413348.hot-update.js",
    "/js/app.1194bdf2ca9d320d277b.hot-update.js": "/js/app.1194bdf2ca9d320d277b.hot-update.js",
    "/js/app.cb3b10b89c617aabb6ae.hot-update.js": "/js/app.cb3b10b89c617aabb6ae.hot-update.js",
    "/js/app.46807f922eba936741bf.hot-update.js": "/js/app.46807f922eba936741bf.hot-update.js",
    "/js/app.38be5dbd22e8de84ace0.hot-update.js": "/js/app.38be5dbd22e8de84ace0.hot-update.js",
    "/js/app.32534655d4081ebfecc1.hot-update.js": "/js/app.32534655d4081ebfecc1.hot-update.js",
    "/js/app.c6efa2afb7edbd62c4bf.hot-update.js": "/js/app.c6efa2afb7edbd62c4bf.hot-update.js",
    "/js/app.2af810791b48d6a39b10.hot-update.js": "/js/app.2af810791b48d6a39b10.hot-update.js",
    "/js/app.57bb77a9b585ba010c50.hot-update.js": "/js/app.57bb77a9b585ba010c50.hot-update.js",
    "/js/app.bc22cc4db0571f79cb0d.hot-update.js": "/js/app.bc22cc4db0571f79cb0d.hot-update.js",
    "/js/app.d341c5e7eebf6504b409.hot-update.js": "/js/app.d341c5e7eebf6504b409.hot-update.js",
    "/js/app.5048cabd403c9547a68d.hot-update.js": "/js/app.5048cabd403c9547a68d.hot-update.js",
    "/js/app.d212e0c372b157236750.hot-update.js": "/js/app.d212e0c372b157236750.hot-update.js",
    "/js/app.deb05b457e9bbc60e6a8.hot-update.js": "/js/app.deb05b457e9bbc60e6a8.hot-update.js",
    "/js/app.d6d1670e6adb2b7b374d.hot-update.js": "/js/app.d6d1670e6adb2b7b374d.hot-update.js",
    "/js/app.3579fbe09462da604c8e.hot-update.js": "/js/app.3579fbe09462da604c8e.hot-update.js",
    "/js/app.1de27bdfa01cc820570a.hot-update.js": "/js/app.1de27bdfa01cc820570a.hot-update.js",
    "/js/app.33a321f9859b7e95013d.hot-update.js": "/js/app.33a321f9859b7e95013d.hot-update.js",
    "/js/app.4097b19e3528a7610b13.hot-update.js": "/js/app.4097b19e3528a7610b13.hot-update.js",
    "/js/app.7244d2002c1b950f518c.hot-update.js": "/js/app.7244d2002c1b950f518c.hot-update.js",
    "/js/app.32cdce35481d352a61d6.hot-update.js": "/js/app.32cdce35481d352a61d6.hot-update.js",
    "/js/app.2b8e07233c0e0f3bacbe.hot-update.js": "/js/app.2b8e07233c0e0f3bacbe.hot-update.js",
    "/js/app.964d870a382411b79ab4.hot-update.js": "/js/app.964d870a382411b79ab4.hot-update.js",
    "/js/app.db03f1a0350d6c282a8b.hot-update.js": "/js/app.db03f1a0350d6c282a8b.hot-update.js",
    "/js/app.dc23a39feaa88dd558dd.hot-update.js": "/js/app.dc23a39feaa88dd558dd.hot-update.js",
    "/js/app.fbdf499dfaf725cc9c16.hot-update.js": "/js/app.fbdf499dfaf725cc9c16.hot-update.js",
    "/js/app.7ba0db6d3779b525467e.hot-update.js": "/js/app.7ba0db6d3779b525467e.hot-update.js",
    "/js/app.611187f891ea95da6ed8.hot-update.js": "/js/app.611187f891ea95da6ed8.hot-update.js",
    "/js/app.7fd2f63c14c6ff268db9.hot-update.js": "/js/app.7fd2f63c14c6ff268db9.hot-update.js",
    "/js/app.914f4bcb3437ddb40937.hot-update.js": "/js/app.914f4bcb3437ddb40937.hot-update.js",
    "/js/app.0e8275bcc36cd3285822.hot-update.js": "/js/app.0e8275bcc36cd3285822.hot-update.js",
    "/js/app.e10fee05ea1521d94e61.hot-update.js": "/js/app.e10fee05ea1521d94e61.hot-update.js",
    "/js/app.ca0bc45e9d5c1b1e8c56.hot-update.js": "/js/app.ca0bc45e9d5c1b1e8c56.hot-update.js",
    "/js/app.cb17ae6d43b55195f7e0.hot-update.js": "/js/app.cb17ae6d43b55195f7e0.hot-update.js",
    "/js/app.6574ba9f8a264039b2ea.hot-update.js": "/js/app.6574ba9f8a264039b2ea.hot-update.js",
    "/js/app.9ab563eb13d5490ed3a0.hot-update.js": "/js/app.9ab563eb13d5490ed3a0.hot-update.js",
    "/js/app.48dae9dc40d4cf4a79a1.hot-update.js": "/js/app.48dae9dc40d4cf4a79a1.hot-update.js",
    "/js/app.2e7411fd045031732929.hot-update.js": "/js/app.2e7411fd045031732929.hot-update.js",
    "/js/app.77550b10afdb6e5ba6a5.hot-update.js": "/js/app.77550b10afdb6e5ba6a5.hot-update.js",
    "/js/app.5219157640e285b59277.hot-update.js": "/js/app.5219157640e285b59277.hot-update.js",
    "/js/app.0b06989ff8cbb58674e8.hot-update.js": "/js/app.0b06989ff8cbb58674e8.hot-update.js",
    "/js/app.61418bd613aa56eae8e4.hot-update.js": "/js/app.61418bd613aa56eae8e4.hot-update.js",
    "/js/app.ab93c17ac9665e6f0cdf.hot-update.js": "/js/app.ab93c17ac9665e6f0cdf.hot-update.js",
    "/js/app.89f20130291edf600db6.hot-update.js": "/js/app.89f20130291edf600db6.hot-update.js",
    "/js/app.c337d73111958eb04d44.hot-update.js": "/js/app.c337d73111958eb04d44.hot-update.js",
    "/js/app.ea87e0995082a3054f1f.hot-update.js": "/js/app.ea87e0995082a3054f1f.hot-update.js",
    "/js/app.699aff2a98554e3ef50c.hot-update.js": "/js/app.699aff2a98554e3ef50c.hot-update.js",
    "/js/app.69088d711a94a6cc2f5b.hot-update.js": "/js/app.69088d711a94a6cc2f5b.hot-update.js",
    "/js/app.a8bd6c791e2384caa59d.hot-update.js": "/js/app.a8bd6c791e2384caa59d.hot-update.js",
    "/js/app.5902df1dccda709e7eed.hot-update.js": "/js/app.5902df1dccda709e7eed.hot-update.js",
    "/js/app.db643480f37103a4c3ab.hot-update.js": "/js/app.db643480f37103a4c3ab.hot-update.js",
    "/js/app.fb0f8f7516b563f686de.hot-update.js": "/js/app.fb0f8f7516b563f686de.hot-update.js",
    "/js/app.a3fee32227b6abf2c6a8.hot-update.js": "/js/app.a3fee32227b6abf2c6a8.hot-update.js",
    "/js/app.494885df79e1ab083ba5.hot-update.js": "/js/app.494885df79e1ab083ba5.hot-update.js",
    "/js/app.db5c5dd149b8a9db238c.hot-update.js": "/js/app.db5c5dd149b8a9db238c.hot-update.js",
    "/js/app.822eb5622fbceeb25483.hot-update.js": "/js/app.822eb5622fbceeb25483.hot-update.js",
    "/js/app.4861c639a9782412a913.hot-update.js": "/js/app.4861c639a9782412a913.hot-update.js",
    "/js/app.b3b5f639943171f9dae5.hot-update.js": "/js/app.b3b5f639943171f9dae5.hot-update.js",
    "/js/app.210629ffb5c9444d2235.hot-update.js": "/js/app.210629ffb5c9444d2235.hot-update.js",
    "/js/app.b14e26548d96ea3a3412.hot-update.js": "/js/app.b14e26548d96ea3a3412.hot-update.js",
    "/js/app.45a7740f47f08e93d576.hot-update.js": "/js/app.45a7740f47f08e93d576.hot-update.js",
    "/js/app.ce985d5e5764ac707421.hot-update.js": "/js/app.ce985d5e5764ac707421.hot-update.js",
    "/js/app.cb098438339fe7796730.hot-update.js": "/js/app.cb098438339fe7796730.hot-update.js",
    "/js/app.0f5de4d94c00d9006a70.hot-update.js": "/js/app.0f5de4d94c00d9006a70.hot-update.js",
    "/js/app.969554db06b40eee5d02.hot-update.js": "/js/app.969554db06b40eee5d02.hot-update.js",
    "/js/app.b4637867879a68081848.hot-update.js": "/js/app.b4637867879a68081848.hot-update.js",
    "/js/app.4c2ae0f7464a1070a623.hot-update.js": "/js/app.4c2ae0f7464a1070a623.hot-update.js",
    "/js/app.4d149d58c836236245f9.hot-update.js": "/js/app.4d149d58c836236245f9.hot-update.js",
    "/js/app.22602a96c292776f7633.hot-update.js": "/js/app.22602a96c292776f7633.hot-update.js",
    "/js/app.397b9d8c63acc6b42426.hot-update.js": "/js/app.397b9d8c63acc6b42426.hot-update.js",
    "/js/app.ea729fb0e8b5b4aef805.hot-update.js": "/js/app.ea729fb0e8b5b4aef805.hot-update.js",
    "/js/app.1a0cb6e3c433bc246a8d.hot-update.js": "/js/app.1a0cb6e3c433bc246a8d.hot-update.js",
    "/js/app.918eb945452095efc936.hot-update.js": "/js/app.918eb945452095efc936.hot-update.js",
    "/js/app.e2f29be6fbdf8dc2ba0b.hot-update.js": "/js/app.e2f29be6fbdf8dc2ba0b.hot-update.js",
    "/js/app.5a829e9bd4864a5e1353.hot-update.js": "/js/app.5a829e9bd4864a5e1353.hot-update.js",
    "/js/app.5a0f6a62fc31daeaee4c.hot-update.js": "/js/app.5a0f6a62fc31daeaee4c.hot-update.js",
    "/js/app.fadf68805a671cef3230.hot-update.js": "/js/app.fadf68805a671cef3230.hot-update.js",
    "/js/app.661516b13966d48a8a02.hot-update.js": "/js/app.661516b13966d48a8a02.hot-update.js",
    "/js/app.e60fa787ee3956b5d12a.hot-update.js": "/js/app.e60fa787ee3956b5d12a.hot-update.js",
    "/js/app.b51cc7c1b7fb73e97a3e.hot-update.js": "/js/app.b51cc7c1b7fb73e97a3e.hot-update.js",
    "/js/app.b9f1a7cf06621f0ac54e.hot-update.js": "/js/app.b9f1a7cf06621f0ac54e.hot-update.js",
    "/js/app.a6470df62b0781942e9a.hot-update.js": "/js/app.a6470df62b0781942e9a.hot-update.js",
    "/js/app.2605d4f1c99d24502759.hot-update.js": "/js/app.2605d4f1c99d24502759.hot-update.js",
    "/js/app.461a70b10fcd0bd4a7ef.hot-update.js": "/js/app.461a70b10fcd0bd4a7ef.hot-update.js",
    "/js/app.cb12a3a16f7dc9c2f088.hot-update.js": "/js/app.cb12a3a16f7dc9c2f088.hot-update.js",
    "/js/app.08327b5f3f851f0c0e81.hot-update.js": "/js/app.08327b5f3f851f0c0e81.hot-update.js",
    "/js/app.a13b8444620048644b46.hot-update.js": "/js/app.a13b8444620048644b46.hot-update.js",
    "/js/app.bc36b09e696a09af58ac.hot-update.js": "/js/app.bc36b09e696a09af58ac.hot-update.js",
    "/js/app.9005d9a32308c15631d8.hot-update.js": "/js/app.9005d9a32308c15631d8.hot-update.js"
}
